go_parallel/__init__.py
go_parallel/config.py
go_parallel/go_parallel.py
go_parallel-0.1.3.dist-info/LICENSE
go_parallel-0.1.3.dist-info/WHEEL
go_parallel-0.1.3.dist-info/METADATA
go_parallel-0.1.3.dist-info/RECORD
