Metadata-Version: 2.1
Name: go-parallel
Version: 0.1.3
Summary: Utility function for running functions asynchronously.
Author: Indrajith Shetty
Author-email: indrajitshetty@gmail.com
Requires-Python: >=3.8,<4.0
Classifier: Programming Language :: Python :: 3
Classifier: Programming Language :: Python :: 3.8
Classifier: Programming Language :: Python :: 3.9
Requires-Dist: pydantic
